[
  {
    "title": "Exploring CP-even scalars of a Two Higgs-doublet model in future e\u2212 p colliders",
    "year": 2017,
    "authors": "Chuene Mosomane and Mukesh Kumar and Alan S Cornell and Bruce Mellado",
    "venue": "Journal of Physics: Conference Series",
    "citations": 11,
    "doi": "https://iopscience.iop.org/article/10.1088/1742-6596/889/1/012004/meta"
  },
  {
    "title": "Machine learning of Ising criticality with spin-shuffling",
    "year": 2022,
    "authors": "Pallab Basu and Jyotirmoy Bhattacharya and Dileep Pavan Surya Jakka and Chuene Mosomane and Vishwanath Shukla",
    "venue": "arXiv preprint arXiv:2203.04012",
    "citations": 6,
    "doi": "https://arxiv.org/abs/2203.04012"
  },
  {
    "title": "Incomplete RG: Hawking-Page transition, C-theorem and relevant scalar deformations of global AdS",
    "year": 2021,
    "authors": "Pallab Basu and Pranav Kumar and Chuene Mosomane",
    "venue": "arXiv preprint arXiv:2112.07750",
    "citations": 2,
    "doi": "https://arxiv.org/abs/2112.07750"
  },
  {
    "title": "Two Higgs-doublet models in future e\u2212 p colliders",
    "year": 2018,
    "authors": "Chuene Mosomane",
    "venue": "N/A",
    "citations": 0,
    "doi": "https://search.proquest.com/openview/9d604f23fdf50319a75ba6bd32c9d58e/1?pq-origsite=gscholar&cbl=2026366&diss=y"
  },
  {
    "title": "Using Renormalisation theory to understand how deep neural networks generalises",
    "year": "N/A",
    "authors": "Chuene Mosomane",
    "venue": "N/A",
    "citations": 0,
    "doi": "https://wiredspace.wits.ac.za/server/api/core/bitstreams/f94a7b15-df6f-4613-9924-7592e2ef6b4f/content"
  },
  {
    "title": "Two-Higgs doublet model and the LHC",
    "year": "N/A",
    "authors": "Chuene Mosomane",
    "venue": "N/A",
    "citations": 0,
    "doi": "https://s3.cern.ch/inspire-prod-files-6/6dec6d5b7461dfa2693c895eafc4f711"
  }
]